{
	"m_Bypass": false,
	"m_CorrespondingSourceObject": { "m_Collection": "Generated Audio Mixer Effects", "m_PathID": 0 },
	"m_EffectID": {
		"m_Data_0_": 3608779783,
		"m_Data_1_": 1173253167,
		"m_Data_2_": 894939777,
		"m_Data_3_": 772312243
	},
	"m_EffectName": "Highpass",
	"m_EnableWetMix": false,
	"m_HideFlags": 3,
	"m_MixLevel": {
		"m_Data_0_": 0,
		"m_Data_1_": 0,
		"m_Data_2_": 0,
		"m_Data_3_": 0
	},
	"m_Name": "",
	"m_Parameters": [
		{
			"m_GUID": {
				"m_Data_0_": 459335857,
				"m_Data_1_": 1132987703,
				"m_Data_2_": 4212587933,
				"m_Data_3_": 1926209037
			},
			"m_ParameterName": "Param_0"
		},
		{
			"m_GUID": {
				"m_Data_0_": 2917320769,
				"m_Data_1_": 1127098024,
				"m_Data_2_": 2223526038,
				"m_Data_3_": 3215037756
			},
			"m_ParameterName": "Param_1"
		}
	],
	"m_PrefabAsset": { "m_Collection": "Generated Audio Mixer Effects", "m_PathID": 0 },
	"m_PrefabInstance": { "m_Collection": "Generated Audio Mixer Effects", "m_PathID": 0 },
	"m_SendTarget": { "m_Collection": "Generated Audio Mixer Effects", "m_PathID": 0 }
}